{
    "sum": {
        "imp24": 192.0,
        "x0": 156.0,
        "x16": 136.0,
        "x9": 134.0,
        "x7": 127.0,
        "x12": 123.0,
        "x8": 122.0,
        "x10": 120.0,
        "x17": 120.0,
        "x3": 119.0,
        "x19": 119.0,
        "x4": 115.0,
        "x5": 114.0,
        "x13": 110.0,
        "x2": 108.0,
        "x1": 101.0,
        "x18": 96.0,
        "x23": 92.0,
        "x14": 91.0,
        "x6": 82.0,
        "x22": 81.0,
        "x11": 79.0,
        "x20": 79.0,
        "x15": 70.0,
        "x21": 62.0
    },
    "average": {
        "imp24": 17.4545,
        "x0": 14.1818,
        "x16": 12.3636,
        "x9": 12.1818,
        "x7": 11.5455,
        "x12": 11.1818,
        "x8": 11.0909,
        "x10": 10.9091,
        "x17": 10.9091,
        "x3": 10.8182,
        "x19": 10.8182,
        "x4": 10.4545,
        "x5": 10.3636,
        "x13": 10.0,
        "x2": 9.8182,
        "x1": 9.1818,
        "x18": 8.7273,
        "x23": 8.3636,
        "x14": 8.2727,
        "x6": 7.4545,
        "x22": 7.3636,
        "x11": 7.1818,
        "x20": 7.1818,
        "x15": 6.3636,
        "x21": 5.6364
    }
}