{
    "sum": {
        "imp7": 515.0,
        "imp2": 488.0,
        "imp4": 480.0,
        "imp1": 478.0,
        "imp12": 425.0,
        "imp25": 419.0,
        "imp10": 397.0,
        "imp14": 393.0,
        "imp46": 392.0,
        "imp35": 390.0,
        "imp11": 387.0,
        "imp18": 387.0,
        "imp36": 384.0,
        "imp22": 346.0,
        "imp34": 336.0,
        "imp49": 335.0,
        "imp29": 301.0,
        "imp3": 294.0,
        "imp32": 276.0,
        "x5": 240.0,
        "imp27": 232.0,
        "x6": 231.0,
        "imp47": 230.0,
        "x0": 224.0,
        "x16": 218.0,
        "x20": 218.0,
        "x8": 217.0,
        "x9": 214.0,
        "x17": 211.0,
        "imp40": 211.0,
        "x19": 201.0,
        "imp33": 200.0,
        "x13": 198.0,
        "x24": 197.0,
        "x23": 195.0,
        "imp44": 173.0,
        "x15": 171.0,
        "imp26": 168.0,
        "x31": 165.0,
        "x21": 163.0,
        "x41": 149.0,
        "x28": 142.0,
        "x30": 136.0,
        "x42": 134.0,
        "x48": 125.0,
        "x43": 123.0,
        "x39": 112.0,
        "x37": 94.0,
        "x45": 93.0,
        "x38": 67.0
    },
    "average": {
        "imp7": 46.8182,
        "imp2": 44.3636,
        "imp4": 43.6364,
        "imp1": 43.4545,
        "imp12": 38.6364,
        "imp25": 38.0909,
        "imp10": 36.0909,
        "imp14": 35.7273,
        "imp46": 35.6364,
        "imp35": 35.4545,
        "imp11": 35.1818,
        "imp18": 35.1818,
        "imp36": 34.9091,
        "imp22": 31.4545,
        "imp34": 30.5455,
        "imp49": 30.4545,
        "imp29": 27.3636,
        "imp3": 26.7273,
        "imp32": 25.0909,
        "x5": 21.8182,
        "imp27": 21.0909,
        "x6": 21.0,
        "imp47": 20.9091,
        "x0": 20.3636,
        "x16": 19.8182,
        "x20": 19.8182,
        "x8": 19.7273,
        "x9": 19.4545,
        "x17": 19.1818,
        "imp40": 19.1818,
        "x19": 18.2727,
        "imp33": 18.1818,
        "x13": 18.0,
        "x24": 17.9091,
        "x23": 17.7273,
        "imp44": 15.7273,
        "x15": 15.5455,
        "imp26": 15.2727,
        "x31": 15.0,
        "x21": 14.8182,
        "x41": 13.5455,
        "x28": 12.9091,
        "x30": 12.3636,
        "x42": 12.1818,
        "x48": 11.3636,
        "x43": 11.1818,
        "x39": 10.1818,
        "x37": 8.5455,
        "x45": 8.4545,
        "x38": 6.0909
    }
}