{
    "sum": {
        "imp0": 146.0,
        "imp3": 139.0,
        "imp10": 107.0,
        "imp8": 102.0,
        "imp2": 92.0,
        "imp11": 87.0,
        "imp6": 82.0,
        "imp14": 69.0,
        "x1": 57.0,
        "x5": 46.0,
        "x7": 44.0,
        "x9": 44.0,
        "x4": 40.0,
        "x13": 32.0,
        "x12": 26.0
    },
    "average": {
        "imp0": 13.2727,
        "imp3": 12.6364,
        "imp10": 9.7273,
        "imp8": 9.2727,
        "imp2": 8.3636,
        "imp11": 7.9091,
        "imp6": 7.4545,
        "imp14": 6.2727,
        "x1": 5.1818,
        "x5": 4.1818,
        "x7": 4.0,
        "x9": 4.0,
        "x4": 3.6364,
        "x13": 2.9091,
        "x12": 2.3636
    }
}