{
    "sum": {
        "imp18": 1121.0,
        "imp6": 1092.0,
        "imp36": 1015.0,
        "imp13": 990.0,
        "imp50": 976.0,
        "imp44": 966.0,
        "imp66": 952.0,
        "imp30": 943.0,
        "imp23": 939.0,
        "imp35": 916.0,
        "imp38": 916.0,
        "imp43": 893.0,
        "imp64": 886.0,
        "imp51": 875.0,
        "imp92": 872.0,
        "imp95": 871.0,
        "imp27": 867.0,
        "imp93": 858.0,
        "imp68": 852.0,
        "imp61": 824.0,
        "imp42": 821.0,
        "imp105": 796.0,
        "imp53": 788.0,
        "imp101": 720.0,
        "imp91": 694.0,
        "imp108": 686.0,
        "imp72": 684.0,
        "imp94": 678.0,
        "imp49": 670.0,
        "x5": 668.0,
        "imp85": 642.0,
        "x0": 639.0,
        "x4": 624.0,
        "x20": 617.0,
        "x8": 614.0,
        "x3": 610.0,
        "x24": 607.0,
        "x10": 601.0,
        "x17": 598.0,
        "x34": 597.0,
        "x12": 594.0,
        "x16": 589.0,
        "x2": 577.0,
        "x15": 576.0,
        "x32": 570.0,
        "x19": 569.0,
        "x7": 565.0,
        "imp63": 564.0,
        "x25": 559.0,
        "x14": 554.0,
        "x21": 545.0,
        "x29": 545.0,
        "imp41": 545.0,
        "x11": 516.0,
        "x1": 513.0,
        "imp107": 512.0,
        "x9": 507.0,
        "x33": 502.0,
        "imp106": 495.0,
        "imp104": 493.0,
        "x28": 492.0,
        "x22": 489.0,
        "x31": 484.0,
        "x26": 482.0,
        "imp96": 475.0,
        "imp70": 472.0,
        "x65": 469.0,
        "x40": 467.0,
        "imp81": 461.0,
        "x39": 459.0,
        "imp54": 456.0,
        "x45": 453.0,
        "x55": 453.0,
        "x37": 446.0,
        "x46": 425.0,
        "x59": 408.0,
        "x52": 407.0,
        "x76": 405.0,
        "x80": 401.0,
        "x67": 396.0,
        "x48": 394.0,
        "x60": 373.0,
        "x57": 367.0,
        "x58": 361.0,
        "x79": 358.0,
        "x88": 355.0,
        "x82": 354.0,
        "x100": 347.0,
        "x97": 346.0,
        "x71": 344.0,
        "x90": 344.0,
        "x78": 343.0,
        "x47": 339.0,
        "x86": 320.0,
        "x75": 310.0,
        "x62": 301.0,
        "x69": 299.0,
        "x109": 295.0,
        "x103": 282.0,
        "x84": 277.0,
        "x74": 274.0,
        "x87": 268.0,
        "x83": 265.0,
        "x98": 260.0,
        "x56": 246.0,
        "x77": 242.0,
        "x73": 222.0,
        "x89": 218.0,
        "x99": 206.0,
        "x102": 196.0
    },
    "average": {
        "imp18": 101.9091,
        "imp6": 99.2727,
        "imp36": 92.2727,
        "imp13": 90.0,
        "imp50": 88.7273,
        "imp44": 87.8182,
        "imp66": 86.5455,
        "imp30": 85.7273,
        "imp23": 85.3636,
        "imp35": 83.2727,
        "imp38": 83.2727,
        "imp43": 81.1818,
        "imp64": 80.5455,
        "imp51": 79.5455,
        "imp92": 79.2727,
        "imp95": 79.1818,
        "imp27": 78.8182,
        "imp93": 78.0,
        "imp68": 77.4545,
        "imp61": 74.9091,
        "imp42": 74.6364,
        "imp105": 72.3636,
        "imp53": 71.6364,
        "imp101": 65.4545,
        "imp91": 63.0909,
        "imp108": 62.3636,
        "imp72": 62.1818,
        "imp94": 61.6364,
        "imp49": 60.9091,
        "x5": 60.7273,
        "imp85": 58.3636,
        "x0": 58.0909,
        "x4": 56.7273,
        "x20": 56.0909,
        "x8": 55.8182,
        "x3": 55.4545,
        "x24": 55.1818,
        "x10": 54.6364,
        "x17": 54.3636,
        "x34": 54.2727,
        "x12": 54.0,
        "x16": 53.5455,
        "x2": 52.4545,
        "x15": 52.3636,
        "x32": 51.8182,
        "x19": 51.7273,
        "x7": 51.3636,
        "imp63": 51.2727,
        "x25": 50.8182,
        "x14": 50.3636,
        "x21": 49.5455,
        "x29": 49.5455,
        "imp41": 49.5455,
        "x11": 46.9091,
        "x1": 46.6364,
        "imp107": 46.5455,
        "x9": 46.0909,
        "x33": 45.6364,
        "imp106": 45.0,
        "imp104": 44.8182,
        "x28": 44.7273,
        "x22": 44.4545,
        "x31": 44.0,
        "x26": 43.8182,
        "imp96": 43.1818,
        "imp70": 42.9091,
        "x65": 42.6364,
        "x40": 42.4545,
        "imp81": 41.9091,
        "x39": 41.7273,
        "imp54": 41.4545,
        "x45": 41.1818,
        "x55": 41.1818,
        "x37": 40.5455,
        "x46": 38.6364,
        "x59": 37.0909,
        "x52": 37.0,
        "x76": 36.8182,
        "x80": 36.4545,
        "x67": 36.0,
        "x48": 35.8182,
        "x60": 33.9091,
        "x57": 33.3636,
        "x58": 32.8182,
        "x79": 32.5455,
        "x88": 32.2727,
        "x82": 32.1818,
        "x100": 31.5455,
        "x97": 31.4545,
        "x71": 31.2727,
        "x90": 31.2727,
        "x78": 31.1818,
        "x47": 30.8182,
        "x86": 29.0909,
        "x75": 28.1818,
        "x62": 27.3636,
        "x69": 27.1818,
        "x109": 26.8182,
        "x103": 25.6364,
        "x84": 25.1818,
        "x74": 24.9091,
        "x87": 24.3636,
        "x83": 24.0909,
        "x98": 23.6364,
        "x56": 22.3636,
        "x77": 22.0,
        "x73": 20.1818,
        "x89": 19.8182,
        "x99": 18.7273,
        "x102": 17.8182
    }
}