{
    "sum": {
        "imp2": 263.0,
        "imp7": 255.0,
        "imp18": 252.0,
        "imp11": 249.0,
        "imp23": 243.0,
        "imp25": 235.0,
        "imp16": 223.0,
        "imp21": 195.0,
        "imp3": 188.0,
        "imp10": 184.0,
        "imp19": 181.0,
        "imp1": 179.0,
        "imp29": 163.0,
        "imp9": 158.0,
        "imp28": 153.0,
        "imp26": 152.0,
        "imp4": 135.0,
        "imp6": 134.0,
        "imp22": 132.0,
        "x0": 128.0,
        "imp24": 122.0,
        "imp8": 110.0,
        "imp15": 109.0,
        "imp14": 105.0,
        "x5": 104.0,
        "imp27": 104.0,
        "x13": 88.0,
        "x12": 84.0,
        "x17": 65.0,
        "x20": 62.0
    },
    "average": {
        "imp2": 23.9091,
        "imp7": 23.1818,
        "imp18": 22.9091,
        "imp11": 22.6364,
        "imp23": 22.0909,
        "imp25": 21.3636,
        "imp16": 20.2727,
        "imp21": 17.7273,
        "imp3": 17.0909,
        "imp10": 16.7273,
        "imp19": 16.4545,
        "imp1": 16.2727,
        "imp29": 14.8182,
        "imp9": 14.3636,
        "imp28": 13.9091,
        "imp26": 13.8182,
        "imp4": 12.2727,
        "imp6": 12.1818,
        "imp22": 12.0,
        "x0": 11.6364,
        "imp24": 11.0909,
        "imp8": 10.0,
        "imp15": 9.9091,
        "imp14": 9.5455,
        "x5": 9.4545,
        "imp27": 9.4545,
        "x13": 8.0,
        "x12": 7.6364,
        "x17": 5.9091,
        "x20": 5.6364
    }
}